Metadata-Version: 1.2
Name: stream-depletion
Version: 1.0.2
Summary: Calculates stream depletion effect of a pumping well using the Jenkins (1968) / Theis (1941) solutions
Home-page: https://github.com/WilcoTerink/stream_depletion
Author: Wilco Terink
Author-email: terinkw@gmail.com
License: GPL-3.0
Keywords: stream depletion well bore pumping superposition jenkins theis transmissivity storativity yield
Platform: UNKNOWN
Classifier: Development Status :: 5 - Production/Stable
Classifier: Intended Audience :: Science/Research
Classifier: Intended Audience :: Developers
Classifier: Intended Audience :: End Users/Desktop
Classifier: Topic :: Scientific/Engineering
Classifier: Topic :: Scientific/Engineering :: Mathematics
Classifier: Topic :: Scientific/Engineering :: Physics
Classifier: License :: OSI Approved :: GNU General Public License v3 (GPLv3)
Classifier: Programming Language :: Python :: 3.6
Requires-Python: >=3.6
